coralogix_opentelemetry/__init__.py
coralogix_opentelemetry/trace/__init__.py
coralogix_opentelemetry/trace/common/__init__.py
coralogix_opentelemetry/trace/samplers/__init__.py
coralogix_opentelemetry/trace/samplers/coralogix_transaction_sampler.py
coralogix_opentelemetry-0.1.2.dist-info/METADATA
coralogix_opentelemetry-0.1.2.dist-info/WHEEL
coralogix_opentelemetry-0.1.2.dist-info/entry_points.txt
coralogix_opentelemetry-0.1.2.dist-info/RECORD
