Metadata-Version: 2.1
Name: coralogix-opentelemetry
Version: 0.1.2
Summary: coralogix extentions for opentelemetry
Author: Nimrod Avni
Author-email: nimrod@coralogix.com
Requires-Python: >=3.8,<4.0
Classifier: Programming Language :: Python :: 3
Classifier: Programming Language :: Python :: 3.8
Classifier: Programming Language :: Python :: 3.9
Classifier: Programming Language :: Python :: 3.10
Classifier: Programming Language :: Python :: 3.11
Classifier: Programming Language :: Python :: 3.12
Requires-Dist: opentelemetry-api (>=1.0.0,<2.0.0)
Requires-Dist: opentelemetry-sdk (>=1.0.0,<2.0.0)
